LICENSE
MANIFEST.in
pypi_readme.rst
readme.md
setup.py
bin/yotta
bin/yt
yotta/__init__.py
yotta/build.py
yotta/clean.py
yotta/config.py
yotta/debug.py
yotta/init.py
yotta/install.py
yotta/licenses.py
yotta/link.py
yotta/link_target.py
yotta/list.py
yotta/login.py
yotta/logout.py
yotta/main.py
yotta/outdated.py
yotta/owners.py
yotta/publish.py
yotta/remove.py
yotta/search.py
yotta/shrinkwrap.py
yotta/start.py
yotta/target.py
yotta/test_subcommand.py
yotta/uninstall.py
yotta/unpublish.py
yotta/update.py
yotta/version.py
yotta/version.txt
yotta/whoami.py
yotta.egg-info/PKG-INFO
yotta.egg-info/SOURCES.txt
yotta.egg-info/dependency_links.txt
yotta.egg-info/requires.txt
yotta.egg-info/top_level.txt
yotta/lib/__init__.py
yotta/lib/access.py
yotta/lib/access_common.py
yotta/lib/auth.py
yotta/lib/cmake_fixups.py
yotta/lib/cmakegen.py
yotta/lib/component.py
yotta/lib/detect.py
yotta/lib/errors.py
yotta/lib/exportkey.py
yotta/lib/folders.py
yotta/lib/fsutils.py
yotta/lib/fsutils_posix.py
yotta/lib/fsutils_win.py
yotta/lib/git_access.py
yotta/lib/github_access.py
yotta/lib/globalconf.py
yotta/lib/hg_access.py
yotta/lib/lazyregex.py
yotta/lib/logging_setup.py
yotta/lib/ordered_json.py
yotta/lib/pack.py
yotta/lib/pool.py
yotta/lib/registry_access.py
yotta/lib/settings.py
yotta/lib/sourceparse.py
yotta/lib/target.py
yotta/lib/utils.py
yotta/lib/validate.py
yotta/lib/vcs.py
yotta/lib/version.py
yotta/lib/schema/module.json
yotta/lib/schema/shrinkwrap.json
yotta/lib/schema/target.json
yotta/lib/templates/base_CMakeLists.txt
yotta/lib/templates/dummy_CMakeLists.txt
yotta/lib/templates/subdir_CMakeLists.txt
yotta/lib/templates/test_CMakeLists.txt
yotta/lib/templates/toolchain.cmake
yotta/options/__init__.py
yotta/options/config.py
yotta/options/debug.py
yotta/options/force.py
yotta/options/noninteractive.py
yotta/options/parser.py
yotta/options/plain.py
yotta/options/registry.py
yotta/options/target.py
yotta/options/verbosity.py
yotta/test/__init__.py
yotta/test/test_components.py
yotta/test/test_config.py
yotta/test/test_git_access.py
yotta/test/test_github_access.py
yotta/test/test_hg_access.py
yotta/test/test_ignores.py
