Metadata-Version: 1.1
Name: yotta
Version: 0.18.4
Summary: Re-usable components for embedded software.
Home-page: https://github.com/ARMmbed/yotta
Author: James Crosby
Author-email: James.Crosby@arm.com
License: Apache-2.0
Keywords: embedded package module dependency management
Platform: UNKNOWN
Classifier: Development Status :: 3 - Alpha
Classifier: Topic :: Utilities
Classifier: License :: OSI Approved :: Apache Software License
Classifier: Environment :: Console
